LICENSE
MANIFEST.in
README.md
pyproject.toml
setup.py
kompozit/__init__.py
kompozit/kompozit.py
kompozit.egg-info/PKG-INFO
kompozit.egg-info/SOURCES.txt
kompozit.egg-info/dependency_links.txt
kompozit.egg-info/entry_points.txt
kompozit.egg-info/requires.txt
kompozit.egg-info/top_level.txt
tests/kompozit_tests.py