Metadata-Version: 2.1
Name: kompozit
Version: 0.2.0b0
Summary: Declarative Configuration Management Tool for Docker Compose.
Home-page: https://github.com/veerendra2/kompozit
Download-URL: https://github.com/veerendra2/kompozit/archive/0.2.0-beta.tar.gz
Author: veerendra2
Author-email: vk.tyk23@simplelogin.com
License: MIT
Project-URL: Documentation, https://veerendra2.gitbook.io/kompozit
Keywords: gitops,cicd,docker-compose,configuration management
Classifier: Development Status :: 4 - Beta
Classifier: Intended Audience :: System Administrators
Classifier: License :: OSI Approved :: Apache Software License
Classifier: Natural Language :: English
Classifier: Operating System :: POSIX :: Linux
Classifier: Programming Language :: Python
Classifier: Programming Language :: Python :: 3
Classifier: Programming Language :: Python :: 3 :: Only
Classifier: Programming Language :: Python :: 3.9
Classifier: Programming Language :: Python :: 3.10
Classifier: Programming Language :: Python :: 3.11
Classifier: Programming Language :: Python :: 3.12
Classifier: Programming Language :: Python :: 3.13
Classifier: Topic :: Utilities
Requires-Python: >=3.9
License-File: LICENSE
Requires-Dist: deepmerge==2.0
Requires-Dist: jsonpatch==1.33
Requires-Dist: PyYAML==6.0.2
